modisconverter/__init__.py
modisconverter/aws/__init__.py
modisconverter/aws/s3.py
modisconverter/common/__init__.py
modisconverter/common/log.py
modisconverter/common/timing.py
modisconverter/common/util.py
modisconverter/common/version.py
modisconverter/common/data/versions.csv
modisconverter/formats/__init__.py
modisconverter/formats/hdf.py
modisconverter/formats/netcdf.py
modisconverter/geo/__init__.py
modisconverter/geo/spatial.py
modisconverter/geo/temporal.py
modisconverter-0.2.0.dist-info/METADATA
modisconverter-0.2.0.dist-info/WHEEL
modisconverter-0.2.0.dist-info/top_level.txt
modisconverter-0.2.0.dist-info/RECORD
