Metadata-Version: 2.1
Name: modisconverter
Version: 0.2.0
Summary: A library for converting MODIS data files
Home-page: https://github.com/nasa/modisconverter
Keywords: MODIS,Converter,HDF4,NetCDF4
Classifier: Development Status :: 2 - Pre-Alpha
Classifier: Intended Audience :: Science/Research
Classifier: Intended Audience :: Developers
Classifier: Operating System :: POSIX :: Linux
Classifier: Programming Language :: Python :: 3
Classifier: Programming Language :: Python :: 3.9
Classifier: Programming Language :: Python :: 3.10
Classifier: Programming Language :: Python :: 3.11
Requires-Python: >=3.9, <4
Requires-Dist: boto3 ==1.18.40
Requires-Dist: GDAL
Requires-Dist: pyhdf ==0.10.5
Requires-Dist: netCDF4 ==1.6.3
Requires-Dist: numpy ==1.24.2
Requires-Dist: pandas ==1.5.3
Requires-Dist: rasterio[s3] ==1.3.6
Provides-Extra: dev
Requires-Dist: ipython ==8.11.0 ; extra == 'dev'
Requires-Dist: pytest ==7.2.2 ; extra == 'dev'
Requires-Dist: pytest-cov ==4.0.0 ; extra == 'dev'
Requires-Dist: nose ==1.3.7 ; extra == 'dev'
Requires-Dist: requests ==2.28.2 ; extra == 'dev'
Requires-Dist: setuptools >=68.1.0 ; extra == 'dev'
Requires-Dist: wheel >=0.41.1 ; extra == 'dev'
Requires-Dist: twine >=4.0.2 ; extra == 'dev'
